{
  "extends": [
    "next/core-web-vitals",
    "next/typescript",
    "prettier"
  ],
  "plugins": [
    "@typescript-eslint",
    "import",
    "unicorn"
  ],
  "rules": {
    "@typescript-eslint/no-explicit-any": "warn",
    "@typescript-eslint/no-unused-vars": "off",
    "no-unused-vars": "off",
    "@typescript-eslint/consistent-type-imports": [
      "warn",
      {
        "prefer": "type-imports",
        "fixStyle": "inline-type-imports"
      }
    ],
    "@typescript-eslint/no-non-null-assertion": "warn",
    "@typescript-eslint/array-type": ["warn", { "default": "array-simple" }],
    "@typescript-eslint/ban-ts-comment": [
      "warn",
      {
        "ts-expect-error": "allow-with-description",
        "ts-ignore": "allow-with-description"
      }
    ],
    "react/no-unescaped-entities": "off",
    "react/jsx-curly-brace-presence": ["warn", { "props": "never", "children": "never" }],
    "react/self-closing-comp": [
      "warn",
      {
        "component": true,
        "html": true
      }
    ],
    "react/jsx-sort-props": [
      "warn",
      {
        "callbacksLast": true,
        "shorthandFirst": true,
        "noSortAlphabetically": false,
        "reservedFirst": true
      }
    ],
    "react/hook-use-state": "warn",
    "import/order": [
      "warn",
      {
        "groups": [
          "builtin",
          "external",
          "internal",
          ["parent", "sibling"],
          "index",
          "object",
          "type"
        ],
        "pathGroups": [
          {
            "pattern": "@/**",
            "group": "internal"
          }
        ],
        "pathGroupsExcludedImportTypes": ["builtin"],
        "newlines-between": "always",
        "alphabetize": {
          "order": "asc",
          "caseInsensitive": true
        }
      }
    ],
    "import/no-duplicates": "warn",
    "import/no-unused-modules": "off",
    "import/no-cycle": "warn",
    "no-console": ["warn", { "allow": ["warn", "error", "info"] }],
    "no-debugger": "error",
    "no-alert": "error",
    "no-var": "error",
    "prefer-const": "error",
    "prefer-template": "warn",
    "prefer-arrow-callback": "warn",
    "prefer-destructuring": ["warn", { "object": true, "array": false }],
    "object-shorthand": "warn",
    "arrow-body-style": ["warn", "as-needed"],
    "curly": ["warn", "multi-line"],
    "eqeqeq": ["error", "always"],
    "no-nested-ternary": "warn",
    "unicorn/filename-case": [
      "warn",
      {
        "cases": {
          "kebabCase": true,
          "pascalCase": true,
          "camelCase": true
        },
        "ignore": ["^\\[.*\\]\\.tsx?$"]
      }
    ],
    "unicorn/prefer-node-protocol": "warn",
    "unicorn/prefer-module": "off",
    "unicorn/better-regex": "warn",
    "unicorn/no-array-for-each": "warn",
    "unicorn/no-for-loop": "warn",
    "unicorn/no-array-reduce": "off",
    "unicorn/prefer-array-flat": "warn",
    "unicorn/prefer-array-some": "warn",
    "unicorn/prefer-date-now": "warn",
    "unicorn/prefer-includes": "warn",
    "unicorn/prefer-string-starts-ends-with": "warn",
    "unicorn/prefer-string-slice": "warn",
    "unicorn/throw-new-error": "error"
  },
  "settings": {
    "import/resolver": {
      "typescript": {
        "alwaysTryTypes": true,
        "project": "./tsconfig.json"
      }
    }
  },
  "ignorePatterns": [
    "node_modules/",
    ".next/",
    "dist/",
    "build/",
    "coverage/",
    "public/sw.js",
    "next-env.d.ts"
  ],
  "overrides": [
    {
      "files": ["*.js", "*.mjs", "*.cjs"],
      "rules": {
        "@typescript-eslint/no-var-requires": "off",
        "@typescript-eslint/explicit-function-return-type": "off"
      }
    },
    {
      "files": ["**/*.test.*", "**/*.spec.*"],
      "rules": {
        "no-console": "off",
        "@typescript-eslint/no-explicit-any": "off"
      }
    }
  ]
}
